buoyant/config/__init__.py
buoyant/config/_config.py
buoyant/config/_loader.py
buoyant/config/annotations/__init__.py
buoyant/config/annotations/gsm.py
buoyant/config/errors.py
buoyant/config/py.typed
buoyant_config-1.0.0a2.dist-info/WHEEL
buoyant_config-1.0.0a2.dist-info/METADATA
buoyant_config-1.0.0a2.dist-info/RECORD
