Metadata-Version: 2.3
Name: buoyant.config
Version: 1.0.0a2
Summary: A modular and typed yaml configuration system for python with easy secret support
Author: Lucas
Author-email: Lucas <lucas@buoyant.systems>
Requires-Dist: pyyaml>=6.0.3
Requires-Dist: pydantic>=2.12.4
Requires-Dist: google-cloud-secret-manager>=2.25.0
Requires-Dist: google-crc32c>=1.7.1
Requires-Python: >=3.12
